url_filter/__init__.py
url_filter/constants.py
url_filter/exceptions.py
url_filter/fields.py
url_filter/filters.py
url_filter/utils.py
url_filter/validators.py
url_filter/backends/__init__.py
url_filter/backends/base.py
url_filter/backends/django.py
url_filter/backends/plain.py
url_filter/backends/sqlalchemy.py
url_filter/filtersets/__init__.py
url_filter/filtersets/base.py
url_filter/filtersets/django.py
url_filter/filtersets/plain.py
url_filter/filtersets/sqlalchemy.py
url_filter/integrations/__init__.py
url_filter/integrations/drf.py
url_filter/integrations/drf_coreapi.py
django_url_filter-0.3.14.dist-info/AUTHORS.rst
django_url_filter-0.3.14.dist-info/LICENSE.rst
django_url_filter-0.3.14.dist-info/METADATA
django_url_filter-0.3.14.dist-info/WHEEL
django_url_filter-0.3.14.dist-info/top_level.txt
django_url_filter-0.3.14.dist-info/RECORD
